LICENSE
MANIFEST.in
README.md
requirements.txt
setup.cfg
setup.py
AAFTF/AAFTF_main.py
AAFTF/__init__.py
AAFTF/__version__.py
AAFTF/assemble.py
AAFTF/assess.py
AAFTF/filter.py
AAFTF/mito.py
AAFTF/pilon.py
AAFTF/pipeline.py
AAFTF/resources.py
AAFTF/rmdup.py
AAFTF/sort.py
AAFTF/sourpurge.py
AAFTF/trim.py
AAFTF/utility.py
AAFTF/vecscreen.py
AAFTF/version_hardcode.py
AAFTF.egg-info/PKG-INFO
AAFTF.egg-info/SOURCES.txt
AAFTF.egg-info/dependency_links.txt
AAFTF.egg-info/entry_points.txt
AAFTF.egg-info/not-zip-safe
AAFTF.egg-info/requires.txt
AAFTF.egg-info/top_level.txt
AAFTF/data/mito-seed.fasta
AAFTF/data/novoplasty-config.txt