Metadata-Version: 2.1
Name: AAFTF
Version: 0.4.0
Summary: Automated genome assembly, cleanup, and polishing
Home-page: http://github.com/stajichlab/AAFTF
Author: Jason Stajich, Jonathan Palmer
Author-email: jasonstajich.phd@gmail.com
Classifier: Development Status :: 4 - Beta
Classifier: Intended Audience :: Science/Research
Classifier: License :: OSI Approved :: MIT License
Classifier: Topic :: Scientific/Engineering :: Bio-Informatics
Requires: python (>=3.6.0)
License-File: LICENSE
